osmviews/__init__.py
osmviews-0.0.5.dist-info/LICENSE
osmviews-0.0.5.dist-info/METADATA
osmviews-0.0.5.dist-info/WHEEL
osmviews-0.0.5.dist-info/top_level.txt
osmviews-0.0.5.dist-info/RECORD
