Metadata-Version: 2.1
Name: osmviews
Version: 0.0.5
Summary: ranking geo locations based on OpenStreetMap views
Home-page: https://github.com/brawer/osmviews-py
Author: Sascha Brawer
Author-email: sascha@brawer.ch
Project-URL: Bug Tracker, https://github.com/brawer/osmviews-py/issues
Classifier: Programming Language :: Python :: 3
Classifier: License :: OSI Approved :: MIT License
Classifier: Operating System :: OS Independent
Requires-Python: >=3.7
License-File: LICENSE
